nonebot/adapters/afdian/__init__.py
nonebot/adapters/afdian/adapter.py
nonebot/adapters/afdian/bot.py
nonebot/adapters/afdian/config.py
nonebot/adapters/afdian/event.py
nonebot/adapters/afdian/exception.py
nonebot/adapters/afdian/message.py
nonebot/adapters/afdian/payload.py
nonebot/adapters/afdian/utils.py
nonebot_adapter_afdian-0.1.8.dist-info/METADATA
nonebot_adapter_afdian-0.1.8.dist-info/WHEEL
nonebot_adapter_afdian-0.1.8.dist-info/licenses/LICENSE
nonebot_adapter_afdian-0.1.8.dist-info/RECORD
