Metadata-Version: 2.4
Name: nonebot-adapter-afdian
Version: 0.1.8
Summary: 爱发电适配器
Author-email: 17TheWord <17theword@gmail.com>
License-Expression: MIT
License-File: LICENSE
Requires-Python: <4,>=3.10
Requires-Dist: nonebot2[fastapi,httpx]<3,>=2.4.2
Requires-Dist: pydantic!=2.5.0,!=2.5.1,<3.0.0,>=1.10.0
